ax253/__init__.py
ax253/address.py
ax253/decode.py
ax253/fcs.py
ax253/frame.py
ax253/tnc2.py
ax253/util.py
ax253-0.1.5.post1.dist-info/LICENSE
ax253-0.1.5.post1.dist-info/METADATA
ax253-0.1.5.post1.dist-info/WHEEL
ax253-0.1.5.post1.dist-info/top_level.txt
ax253-0.1.5.post1.dist-info/RECORD
