Metadata-Version: 2.1
Name: ax253
Version: 0.1.5.post1
Summary: Experimental pure python ax25 stack.
Author-email: Masen Furer KF7HVM <kf7hvm@0x26.net>
License:                                  Apache License
Project-URL: Homepage, https://github.com/python-aprs/ax253
Keywords: Ham Radio,APRS,ax.25
Classifier: License :: OSI Approved :: Apache Software License
Classifier: Topic :: Communications :: Ham Radio
Classifier: Programming Language :: Python
Classifier: License :: OSI Approved :: Apache Software License
License-File: LICENSE
